{
    "Shader": {
        "info": {
            "date": "1598732180",
            "description": "Day 16 of #raymarching challenge. Sierpinski tetrahedron studies.",
            "flags": 0,
            "hasliked": 0,
            "id": "3tBBWh",
            "likes": 3,
            "name": "Day 16 of #raymarching challenge",
            "published": 3,
            "tags": [
                "raymarching",
                "fractal"
            ],
            "usePreview": 0,
            "username": "illus0r",
            "viewed": 277
        },
        "renderpass": [
            {
                "code": "#define textureCube texture\n\n#define MAX_STEPS 100\n#define MAX_DIST 100.\n#define EPSILON 0.0001\n#define PI 3.14159265\n#define IVORY 1.\n#define BLUE 2.\n#define BLACK 3.\n#define RED 4.\n\n#define PHI (sqrt(5.)*0.5 + 0.5)\n#define iTime (iTime / 10.1)\n\n\n\nmat2 Rot(float a) {\n    float s = sin(a), c = cos(a);\n\treturn mat2(c, -s, s, c);\n}\n\nfloat sdBox( vec3 p, vec3 b )\n{\n  vec3 q = abs(p) - b;\n  return length(max(q,0.0)) + min(max(q.x,max(q.y,q.z)),0.0);\n}\n\nvec2 polarToDecart(vec2 polar) {\n    float alpha = polar.x;\n    float R = polar.y;\n    float x = sin(alpha) * R;\n    float y = cos(alpha) * R;\n    return vec2(x, y);\n}\n\nvec2 decartToPolar(vec2 decart) {\n    float alpha = atan(decart.x, decart.y);\n    float R = length(decart);\n    return vec2(alpha, R);\n}\n\nfloat DE(vec3 z)\n{\n    // FIXME\n    z.x += 5. * sin(iTime);\n    z.y += 5. * sin(iTime);\n    z.z += 5. * cos(iTime);\n    float r;\n    int n = 0;\n    float Scale = 1.1;\n    float Move = 10.;\n    while (n < 15) {\n        // z.xy *= Rot(0.3 * iTime);\n        z.yx *= Rot(iTime * .5);\n       if(z.x+z.y<0.) z.xy = -z.yx; // fold 1\n       if(z.x+z.z<0.) z.xz = -z.zx; // fold 2\n       if(z.y+z.z<0.) z.zy = -z.yz; // fold 3\t\n        // z-=2.0 * min(0.0, 1.) * n1;\n       z = z*Scale - Move*(Scale-1.0);\n    //     vec3 n1 = vec3(0.4 * sin(iTime), 0.9, -0.1 * sin(iTime));\n    //    float t = dot(z,n1); if (t<0.0) { z-=5.0*t*n1; }\n    //     n1 = n1.zyx;\n    //    t = dot(z,n1); if (t<0.0) { z-=5.0*t*n1; }\n       n++;\n    }\n    return (length(z)) * pow(Scale, -float(n)) - 0.5;\n}\n\nfloat sdColumn(vec3 p, float width) {\n    // float box = sdBox(p, vec3(width, 10., width));\n    p *= 5.;\n    float fractal = DE(p) / 5.;\n    // float column = max(fractal, box);\n    // return column;\n    // return fractal + abs((p.x + p.z ) / 1.);\n    return fractal;\n}\n\n// ↓↓↓↓↓↓↓↓↓↓↓↓↓↓↓↓↓↓↓↓↓↓↓↓↓\nvec2 getDist(vec3 p) {\n    vec2 ar = decartToPolar(p.xz);\n    float a = ar.x, r = ar.y;\n    float astep = 2. * PI / 8.; // number of rays\n    a = mod(a, astep);\n    a -= astep / 2.;\n    a = abs(a);\n    p.xz = polarToDecart(vec2(a, r));\n    // float cyl = length(p.xz - vec2(0, 2)) - 0.2;\n    p.xz *= Rot(iTime + p.y * 0.1);\n    float column = sdColumn(p, 2.5);\n    return vec2(column, RED);\n    // return cyl < column? vec2(cyl, BLACK) : vec2(column, IVORY);\n//   return vec2(max(DE(p), length(p.xz+vec2(1)) - 0.1), BLUE);\n//   return vec2(DE(p) + length(p) - 4., BLUE);\n}\n// ↑↑↑↑↑↑↑↑↑↑↑↑↑↑↑↑↑↑↑↑↑↑↑↑↑\n\n\n\n\n\n\n\n\n\nvec3 rayMarch(vec3 ro, vec3 rd) {\n\tfloat d = 0.;\n    float info = 0.;\n    //float glow = 0.;\n    float minAngleToObstacle = 1e10;\n    for (int i = 0; i < MAX_STEPS; i++) {\n    \tvec2 distToClosest = getDist(ro + rd * d);\n        minAngleToObstacle = min(minAngleToObstacle, atan(distToClosest.x, d));\n        d += abs(distToClosest.x);\n        info = distToClosest.y;\n        if(abs(distToClosest.x) < EPSILON || d > MAX_DIST) {\n        \tbreak;\n        }\n    }\n    return vec3(d, info, minAngleToObstacle);\n}\n\nvec3 getNormal(vec3 p) {\n    vec2 e = vec2(EPSILON, 0.);\n    vec3 n = getDist(p).x - vec3(getDist(p - e.xyy).x,\n                               getDist(p - e.yxy).x,\n                               getDist(p - e.yyx).x);\n\treturn normalize(n);\n}\n\n\n\nvec3 getRayDirection (vec3 ro, vec2 uv, vec3 lookAt) {\n    vec3 rd;\n    rd = normalize(vec3(uv - vec2(0, 0.), 1.));\n    vec3 lookTo = lookAt - ro;\n    float horizAngle = acos(dot(lookTo.xz, rd.xz) / length(lookTo.xz) * length(rd.xz));\n    rd.xz *= Rot(horizAngle);\n    return rd;\n}\n\nvec3 getRayDir(vec2 uv, vec3 p, vec3 l, float z) {\n    vec3 f = normalize(l-p),\n        r = normalize(cross(vec3(0,1,0), f)),\n        u = cross(f,r),\n        c = f*z,\n        i = c + uv.x*r + uv.y*u,\n        d = normalize(i);\n    return d;\n}\n\n\nvoid mainImage(out vec4 fragColor, in vec2 fragCoord )\n{\n    vec2 uv = (fragCoord-.5*iResolution.xy)/iResolution.y;\n\n    // ray origin\n    float camRadius = 7.;\n    vec3 ro = vec3(camRadius * sin(iTime * .0), 0, camRadius * cos(iTime * .0));\n    ro.xz *= Rot(iMouse.x / iResolution.x * PI * 2.);\n    float zoom = 1.100;\n\n    // ray direction\n    vec3 rd = getRayDir(uv, ro, vec3(0), 1.);\n\n    vec3 rm = rayMarch(ro, rd);\n    float d = rm[0];\n    float info = rm[1];\n\n    vec3 colorBg = vec3(.0);\n    vec3 color;\n    color = vec3(1);\n    // color = textureCube(iChannel0, rd).xyz;\n    vec3 light = vec3(camRadius * cos(iTime * .2), 20, camRadius * sin(iTime * .2));\n    //light.xz *= Rot(iTime);\n    vec3 p = ro + rd * d;\n    if (d < MAX_DIST) {\n        vec3 n = getNormal(p);\n        //n.zy *= Rot(iTime);\n    \t// color = vec3( n * 0.5 + 0.5 );\n\n        //color *= info;\n        // vec3 tex = boxmap(u_tex_bg, ro + rd * d, n, 32.0 ).xyz;//\n        // self shadeing\n        // drop shadows\n        // trying to raymarch to the light for MAX_DIST\n        // and if we hit something, it's shadow\n        vec3 dirToLight = normalize(light - p);\n        vec3 rayMarchLight = rayMarch(p + dirToLight * .06, dirToLight);\n        float distToObstable = rayMarchLight.x;\n        float distToLight = length(light - p);\n        // if (distToObstable < distToLight) {\n        //     color *=  0.;\n        // }\n\n        // smooth shadows\n        float shadow = smoothstep(0.0, .15, rayMarchLight.z / PI);\n        color += .1 + .9 * shadow;\n\n        // reflection\n        // vec3 ref = reflect(rd, n);\n        // color += textureCube(iChannel0, ref).xyz;\n\n        // // refraction\n        // float e = 0.2;\n        // for (int i = 0; i < 2; i++) {\n        //     rd = refract(rd, n, 1. - e);\n        //     // rd = reflect(rd, n);\n        //     ro = p + rd * 0.05;\n        //     rm = rayMarch(ro, rd);\n        //     d = rm[0];\n        //     if (d > MAX_DIST) break;\n        //     p = ro + rd * d;\n        //     n = getNormal(p);\n\n        //     rd = refract(rd, -n, 1. + e);\n        //     // rd = reflect(rd, n);\n        //     ro = p + rd * 0.05;\n        //     rm = rayMarch(ro, rd);\n        //     d = rm[0];\n        //     if (d > MAX_DIST) break;\n        //     p = ro + rd * d;\n        //     n = getNormal(p);\n        // }\n        // color *= textureCube(iChannel0, rd).xyz;\n\n        // // reflection\n        // for (int i = 0; i < 2; i++) {\n        //     rd = reflect(rd, n);\n        //     ro = p + rd * 0.05;\n        //     rm = rayMarch(ro, rd);\n        //     d = rm[0];\n        //     if (d > MAX_DIST) break;\n        //     p = ro + rd * d;\n        //     n = getNormal(p);\n\n        //     rd = reflect(rd, n);\n        //     ro = p + rd * 0.05;\n        //     rm = rayMarch(ro, rd);\n        //     d = rm[0];\n        //     if (d > MAX_DIST) break;\n        //     p = ro + rd * d;\n        //     n = getNormal(p);\n        // }\n        // color = mix(textureCube(iChannel0, rd).xyz, color, 0.5);\n\n        //rm = rayMarch(p + ref * 0.1, ref);\n        // color = vec3(d);\n\n\n\n        // tex *= color_bw;\n        // color = tex;\n        // color += 0.6 + vec3( color_bw );\n        // coloring\n        if (d < MAX_DIST) {\n            if (info == IVORY) {\n                color = vec3(.4 * (dot(n, normalize(light - p))) + 1.);\n                // color *= vec3(0.832,0.800,0.849);\n            }\n            else if (info == BLUE) {\n                color *= vec3(0.810,0.256,0.397);\n            }\n           else if (info == RED) {\n                color = vec3(.4 * (dot(n, normalize(light - p))) + 1.);\n                color *= vec3(0.810,0.256,0.397);\n            }\n            else if (info == BLACK) {\n                color = vec3(0.);//vec3(.0 + 0.2 * (dot(n, normalize(light - p))) + 1.);\n                // color *= vec3(0.130,0.130,0.130);\n                // color *= 5. / length(p.xz);\n            }\n            // color = mix(color, colorBg, smoothstep(20., 28., d));\n        }\n    }\n\n    fragColor = vec4(color, 1);\n}",
                "description": "",
                "inputs": [],
                "name": "Image",
                "outputs": [
                    {
                        "channel": 0,
                        "id": 37
                    }
                ],
                "type": "image"
            }
        ],
        "ver": "0.1"
    }
}