{
    "Shader": {
        "info": {
            "date": "1535340399",
            "description": "tempIntensity 时间。\n",
            "flags": 0,
            "hasliked": 0,
            "id": "4tVcRW",
            "likes": 3,
            "name": "girlscam 错乱效果",
            "published": 3,
            "tags": [
                "girlscam"
            ],
            "usePreview": 0,
            "username": "liuhaidong",
            "viewed": 733
        },
        "renderpass": [
            {
                "code": "\n//返回小数部分\nfloat fracFunc (float x)\n{\n    return x - floor(x);\n}\n\n//\nfloat nrand(float x, float y)\n{\n    return fracFunc(sin(dot(vec2(x, y), vec2(12.9898, 78.233))) * 43758.5453);\n}\n//两者之间插值\nfloat lerpFunc(float a, float b, float w) {\n  return a + w*(b-a);\n}\n\nvoid mainImage( out vec4 fragColor, in vec2 fragCoord )\n{\n    vec2 uv = fragCoord.xy / iResolution.xy;\n                \n    float tempIntensity = iTime;\n    \n\n    //scanLineJitter 扫描线抖动效果\n    float scanLineJitter = abs(sin(tempIntensity));//取值0-1\n    float sl_thresh = clamp(1.0-scanLineJitter*1.2,0.0,1.0);\n    float sl_disp = 0.002 + pow(scanLineJitter, 3.0) * 0.05;        \n    vec2 slj_uv = vec2(sl_disp,sl_thresh); // (displacement, threshold)    \n    \n    //colorDrift 颜色\n    float amount = 0.2;//取值0-1\n    amount *= 0.04;\n    float time = 1.0 *606.11;\n    vec2 colorDrift = vec2(amount,time);     // (amount, time)\n    \n    // Scan line jitter 抖动效果\n    float jitter = nrand(uv.y, scanLineJitter) * 2.0 - 1.0;\n    jitter *= step(slj_uv.y, abs(jitter)) * slj_uv.x;\n\n    \n    // Color drift\n    float drift = sin(colorDrift.y) * colorDrift.x;\n\n    vec2 src1uv = vec2(fracFunc(uv.x + jitter ),uv.y);\n    vec4 src1 = texture(iChannel0, src1uv);\n    \n    vec2 src2uv = vec2(fracFunc(uv.x + jitter +drift),uv.y);\n    vec4 src2 = texture(iChannel0, src2uv);\n\n    fragColor = vec4(src1.r, src2.g, src1.b, 1.0);\n    \n}",
                "description": "",
                "inputs": [
                    {
                        "channel": 0,
                        "ctype": "texture",
                        "id": 5,
                        "published": 1,
                        "sampler": {
                            "filter": "mipmap",
                            "internal": "byte",
                            "srgb": "false",
                            "vflip": "true",
                            "wrap": "repeat"
                        },
                        "src": "/media/a/8de3a3924cb95bd0e95a443fff0326c869f9d4979cd1d5b6e94e2a01f5be53e9.jpg"
                    }
                ],
                "name": "Image",
                "outputs": [
                    {
                        "channel": 0,
                        "id": 37
                    }
                ],
                "type": "image"
            }
        ],
        "ver": "0.1"
    }
}