{
    "Shader": {
        "info": {
            "date": "1683343759",
            "description": "yep",
            "flags": 0,
            "hasliked": 0,
            "id": "Dt33Dl",
            "likes": 6,
            "name": "just fun 230505",
            "published": 3,
            "tags": [
                "optics",
                "transmission",
                "nonphysical"
            ],
            "usePreview": 0,
            "username": "elenzil",
            "viewed": 168
        },
        "renderpass": [
            {
                "code": "#define RES    (iResolution.xy)\n#define MINRES (min(RES.x, RES.y))\n\nfloat gVPZoom     =   0.8;\nfloat gVPEps      =   1e9;        // viewport epsilon\nfloat gVPLW       =   1e9;        // viewport linewidth\n\n\nfloat viewportFromScreen(in float D) {\n    return D * 2.0 / MINRES / gVPZoom;\n}\n\nvec2 viewportFromScreen(in vec2 XY) {\n    return vec2(viewportFromScreen(XY.x - RES.x / 2.0),\n                viewportFromScreen(XY.y - RES.y / 2.0));\n}\n\nvoid mainImage(out vec4 RGBA, in vec2 XY)\n{\n    vec2 xy = viewportFromScreen(XY);\n    gVPEps  = viewportFromScreen(2.0);\n    gVPLW   = viewportFromScreen(2.0);\n\n    float d = 1e9;\n    d =  min( d, smoothstep(0.0, gVPEps, abs(sin(xy.x * 3.0 + iTime)) - gVPLW * 4.0 ));\n    d = -min(-d, abs(xy.y) - gVPLW * 3.0);\n    vec3 c = vec3(0.8);\n    c = mix(c, vec3(0.5, 0.1, 0.1), smoothstep(gVPEps, 0.0, d));\n\n    xy.y /= sin(xy.x * 3.0 + iTime);\n    float q = length(xy) - 0.9;\n    c = mix(c, vec3(0.6, 0.7, 0.8), smoothstep(gVPEps, 0.0, q));\n    d = abs(q) - gVPLW;\n\n    c = mix(c, vec3(0.0), smoothstep(gVPEps, 0.0, d));\n\n\n    RGBA = vec4(c, 1.0);\n}",
                "description": "",
                "inputs": [],
                "name": "Image",
                "outputs": [
                    {
                        "channel": 0,
                        "id": 37
                    }
                ],
                "type": "image"
            }
        ],
        "ver": "0.1"
    }
}