{
    "Shader": {
        "info": {
            "date": "1713480900",
            "description": "Simple example with the current frame beeing modified by the previous one",
            "flags": 34,
            "hasliked": 0,
            "id": "Mc3Xzn",
            "likes": 0,
            "name": "Fork Previous f supernlogn 891",
            "published": 3,
            "tags": [
                "frame",
                "backbuffer",
                "previous"
            ],
            "usePreview": 0,
            "username": "supernlogn",
            "viewed": 129
        },
        "renderpass": [
            {
                "code": "void mainImage( out vec4 fragColor, in vec2 fragCoord )\n{\n    vec2 uv = fragCoord.xy / iResolution.xy;\n    vec4 draw = texture(iChannel0,uv);\n    vec4 draw2 = texture(iChannel1,uv);\n    fragColor = vec4(abs(draw2.rgb - draw.rgb),1.);\n}",
                "description": "",
                "inputs": [
                    {
                        "channel": 1,
                        "ctype": "webcam",
                        "id": 31,
                        "published": 1,
                        "sampler": {
                            "filter": "linear",
                            "internal": "byte",
                            "srgb": "false",
                            "vflip": "true",
                            "wrap": "clamp"
                        },
                        "src": "/presets/webcam.png"
                    },
                    {
                        "channel": 0,
                        "ctype": "buffer",
                        "id": 257,
                        "published": 1,
                        "sampler": {
                            "filter": "linear",
                            "internal": "byte",
                            "srgb": "false",
                            "vflip": "true",
                            "wrap": "clamp"
                        },
                        "src": "/media/previz/buffer00.png"
                    }
                ],
                "name": "Image",
                "outputs": [
                    {
                        "channel": 0,
                        "id": 37
                    }
                ],
                "type": "image"
            },
            {
                "code": "void mainImage( out vec4 fragColor, in vec2 fragCoord )\n{\n    float time = iTime;\n    vec2 uv = fragCoord.xy / iResolution.xy;\n    vec4 draw = texture(iChannel0,uv);\n    fragColor = draw;\n}",
                "description": "",
                "inputs": [
                    {
                        "channel": 0,
                        "ctype": "webcam",
                        "id": 31,
                        "published": 1,
                        "sampler": {
                            "filter": "linear",
                            "internal": "byte",
                            "srgb": "false",
                            "vflip": "true",
                            "wrap": "clamp"
                        },
                        "src": "/presets/webcam.png"
                    }
                ],
                "name": "Buffer A",
                "outputs": [
                    {
                        "channel": 0,
                        "id": 257
                    }
                ],
                "type": "buffer"
            }
        ],
        "ver": "0.1"
    }
}