{
    "Shader": {
        "info": {
            "date": "1505980831",
            "description": "test whether a texture is tilable\n\nnot tilable:  organic1, wood, (& London, of course)",
            "flags": 0,
            "hasliked": 0,
            "id": "Mtfyzs",
            "likes": 2,
            "name": "test texture wrap",
            "published": 3,
            "tags": [
                "utils",
                "tilable"
            ],
            "usePreview": 0,
            "username": "FabriceNeyret2",
            "viewed": 740
        },
        "renderpass": [
            {
                "code": "void mainImage( out vec4 O, in vec2 U )\n{\n\tO = texture(iChannel0, .4*iTime + U / iResolution.xy ).rrrr;\n    //if (iChannelResolution[0].z == 1.) O = O.rrrr;\n}",
                "description": "",
                "inputs": [
                    {
                        "channel": 0,
                        "ctype": "texture",
                        "id": 47,
                        "published": 1,
                        "sampler": {
                            "filter": "mipmap",
                            "internal": "byte",
                            "srgb": "false",
                            "vflip": "true",
                            "wrap": "repeat"
                        },
                        "src": "/media/a/ad56fba948dfba9ae698198c109e71f118a54d209c0ea50d77ea546abad89c57.png"
                    }
                ],
                "name": "Image",
                "outputs": [
                    {
                        "channel": 0,
                        "id": 37
                    }
                ],
                "type": "image"
            }
        ],
        "ver": "0.1"
    }
}