{
    "Shader": {
        "info": {
            "date": "1646851604",
            "description": "more testing",
            "flags": 0,
            "hasliked": 0,
            "id": "sdBfRd",
            "likes": 2,
            "name": "Another Weird wave",
            "published": 3,
            "tags": [
                "wobble",
                "warp",
                "trippy",
                "weird",
                "sinwave",
                "insanity"
            ],
            "usePreview": 0,
            "username": "cooldude999",
            "viewed": 232
        },
        "renderpass": [
            {
                "code": "vec3 hueshift(vec3 c, float s){\n    vec3 m=vec3(cos(s),s=sin(s)*.5700,-s);\n    return c*mat3(m+=(1.-m.x)/3.,m.zxy,m.yzx);\n}\n\nvoid mainImage( out vec4 fragColor, in vec2 fragCoord )\n{\n    \n    \n    \n    float timeMulti = 30.09;\n    float timeDiv = 6.3;\n\t// Get the UV Coordinate of your texture or Screen Texture, yo!\n\tvec2 uv = fragCoord.xy / iResolution.xy;\n\t\n\t// Flip that shit..? \n\tuv.x + 2.0 * iTime;\n    uv.y * 2.0 * iTime / uv.y;\n\t\n\t// the funny doings!\n    \n    //some weird spinny wobble thing !! :]? ??\n\tuv.x += sin(uv.x*1.0*iTime / 9.0)/20.0;  //some weird ripple effect\n    uv.y += sin(uv.y*0.8/iTime + timeDiv)/1.0; //intro stretch\n\n\tuv.xy += sin(uv.x-10.0+iTime)*0.29; //wave one\n\n    uv.yx += sin(uv.y+10.0+iTime)/10.0; //wave two\n\n    uv.y += sin(uv.x * 10.0+iTime + 0.03)*0.08;\n\n\n \n\t\n\t\n\t\n\t\n\t\n    \n    \n    vec4 color = texture(iChannel0, uv);\n    fragColor = color;\n    \n    \n    \n    \n    \n}",
                "description": "",
                "inputs": [
                    {
                        "channel": 0,
                        "ctype": "texture",
                        "id": 28,
                        "published": 1,
                        "sampler": {
                            "filter": "nearest",
                            "internal": "byte",
                            "srgb": "false",
                            "vflip": "true",
                            "wrap": "repeat"
                        },
                        "src": "/media/a/85a6d68622b36995ccb98a89bbb119edf167c914660e4450d313de049320005c.png"
                    }
                ],
                "name": "Image",
                "outputs": [
                    {
                        "channel": 0,
                        "id": 37
                    }
                ],
                "type": "image"
            }
        ],
        "ver": "0.1"
    }
}