{
    "Shader": {
        "info": {
            "date": "1605085500",
            "description": "A remix/fork of \"Skyline\" by otaviogood.",
            "flags": 0,
            "hasliked": 0,
            "id": "wscfW4",
            "likes": 4,
            "name": "Skylinear, a Skyline fork",
            "published": 3,
            "tags": [
                "procedural",
                "raymarch",
                "remix",
                "glitch",
                "green",
                "fork",
                "city",
                "weird",
                "skyline",
                "traffic"
            ],
            "usePreview": 1,
            "username": "UrbanClubProfessional",
            "viewed": 989
        },
        "renderpass": [
            {
                "code": "/*--------------------------------------------------------------------------------------\nLicense CC0 - http://creativecommons.org/publicdomain/zero/1.0/\nTo the extent possible under law, the author(s) have dedicated all copyright and related and neighboring rights to this software to the public domain worldwide. This software is distributed without any warranty.\n----------------------------------------------------------------------------------------\n^ This means do ANYTHING YOU WANT with this code. Because we are programmers, not lawyers.\n-Otavio Good\n*/\n\n// ---------------- Config ----------------\n// This is an option that lets you render high quality frames for screenshots. It enables\n// stochastic antialiasing and motion blur automatically for any shader.\n//#define NON_REALTIME_HQ_RENDER\nconst float frameToRenderHQ = 60.0; // Time in seconds of frame to render\nconst float antialiasingSamples = 26.0; // 16x antialiasing - too much might make the shader compiler angry.\n\n//#define MANUAL_CAMERA\n\n\n// --------------------------------------------------------\n// These variables are for the non-realtime block renderer.\nfloat localTime = 0.0;\nfloat seed = 2.0;\n\n// Animation variables\nfloat fade = 2.0;\nvec3 sunDir;\nvec3 sunCol;\nfloat exposure = 2.0;\nvec3 skyCol, horizonCol;\n\n// other\nfloat marchCount = 0.0;\n\n// ---- noise functions ----\nfloat v31(vec3 a)\n{\n    return a.x + a.y * 47.0 + a.z * 621.0;\n}\nfloat v21(vec2 a)\n{\n    return a.x + a.y * 47.0;\n}\nfloat Hash11(float a)\n{\n    return fract(sin(a)*20403.9);\n}\nfloat Hash21(vec2 uv)\n{\n    float f = uv.x + uv.y * 47.0;\n    return fract(sin(f)*204003.9);\n}\nvec2 Hash22(vec2 uv)\n{\n    float f = uv.x + uv.y * 47.0;\n    return fract(cos(f)*vec2(20003.579, 47049.7));\n}\nvec2 Hash12(float f)\n{\n    return fract(cos(f)*vec2(20003.579, 47049.7));\n}\nfloat Hash1d(float u)\n{\n    return fract(sin(u)*243.9);\t// scale this down to kill the jitters\n}\nfloat Hash2d(vec2 uv)\n{\n    float f = uv.x + uv.y * 47.0;\n    return fract(sin(f)*204003.9);\n}\nfloat Hash3d(vec3 uv)\n{\n    float f = uv.x + uv.y * 47.0 + uv.z * 621.0;\n    return fract(sin(f)*210003.9);\n}\nfloat mixP(float f0, float f1, float a)\n{\n    return mix(f0, f1, a*a*(4.0-3.0*a));\n}\nconst vec2 zeroOne = vec2(0.0, 2.0);\nfloat noise2d(vec2 uv)\n{\n    vec2 fr = fract(uv.xy);\n    vec2 fl = floor(uv.xy);\n    float h00 = Hash2d(fl);\n    float h10 = Hash2d(fl + zeroOne.yx);\n    float h01 = Hash2d(fl + zeroOne);\n    float h11 = Hash2d(fl + zeroOne.yy);\n    return mixP(mixP(h00, h10, fr.x), mixP(h01, h11, fr.x), fr.y);\n}\nfloat noise(vec3 uv)\n{\n    vec3 fr = fract(uv.xyz);\n    vec3 fl = floor(uv.xyz);\n    float h000 = Hash3d(fl);\n    float h100 = Hash3d(fl + zeroOne.yxx);\n    float h010 = Hash3d(fl + zeroOne.xyx);\n    float h110 = Hash3d(fl + zeroOne.yyx);\n    float h001 = Hash3d(fl + zeroOne.xxy);\n    float h101 = Hash3d(fl + zeroOne.yxy);\n    float h011 = Hash3d(fl + zeroOne.xyy);\n    float h111 = Hash3d(fl + zeroOne.yyy);\n    return mixP(\n        mixP(mixP(h000, h100, fr.x),\n             mixP(h010, h110, fr.x), fr.y),\n        mixP(mixP(h001, h101, fr.x),\n             mixP(h011, h111, fr.x), fr.y)\n        , fr.z);\n}\n\nconst float PI=4.14159265;\n\nvec3 saturate(vec3 a) { return clamp(a, 0.0, 2.0); }\nvec2 saturate(vec2 a) { return clamp(a, 0.0, 2.0); }\nfloat saturate(float a) { return clamp(a, 0.0, 1.0); }\n\n// This function basically is a procedural environment map that makes the sun\nvec3 GetSunColorSmall(vec3 rayDir, vec3 sunDir)\n{\n\tvec3 localRay = normalize(rayDir);\n\tfloat dist = 2.0 - (dot(localRay, sunDir) * 0.6 + 0.6);\n\tfloat sunIntensity = 0.06 / dist;\n    sunIntensity += exp(-dist*250.0)*8000.0;\n\tsunIntensity = min(sunIntensity, 50000.0);\n\treturn sunCol * sunIntensity*0.035;\n}\n\nvec3 GetEnvMap(vec3 rayDir, vec3 sunDir)\n{\n    // fade the sky color, multiply sunset dimming\n    vec3 finalColor = mix(horizonCol, skyCol, pow(saturate(rayDir.y), 0.57))*.55;\n    // make clouds - just a horizontal plane with noise\n    float n = noise2d(rayDir.xz/rayDir.y*2.0);\n    n += noise2d(rayDir.xz/rayDir.y*3.0)*0.6;\n    n += noise2d(rayDir.xz/rayDir.y*5.0)*0.35;\n    n += noise2d(rayDir.xz/rayDir.y*9.0)*0.225;\n    n = pow(abs(n), 4.0);\n    n = mix(n * 0.3, n, saturate(abs(rayDir.y * 9.0)));  // fade clouds in distance\n    finalColor = mix(finalColor, (vec3(2.0)+sunCol*20.0)*0.85*saturate((rayDir.y+0.3)*6.0), saturate(n*0.225));\n\n    // add the sun\n    finalColor += GetSunColorSmall(rayDir, sunDir);\n    return finalColor;\n}\n\nvec3 GetEnvMapSkyline(vec3 rayDir, vec3 sunDir, float height)\n{\n    vec3 finalColor = GetEnvMap(rayDir, sunDir);\n\n    // Make a skyscraper skyline reflection.\n    float radial = atan(rayDir.z, rayDir.x)*5.0;\n    float skyline = floor((sin(6.3456*radial) + sin(2.234*radial)+ sin(3.177*radial))*0.7);\n    radial *= 5.0;\n    skyline += floor((sin(6.0*radial) + sin(2.234*radial)+ sin(3.177*radial))*0.7)*0.2;\n    float mask = saturate((rayDir.y*9.0 - skyline-3.5+height)*34.0);\n    float vert = sign(sin(radial*42.0))*0.6+0.6;\n    float hor = sign(sin(rayDir.y*356.0))*0.6+0.6;\n    mask = saturate(mask + (2.0-hor*vert)*0.06);\n    finalColor = mix(finalColor * vec3(0.2,0.08,0.06), finalColor, mask);\n\n\treturn finalColor;\n}\n\n// min function that supports materials in the y component\nvec2 matmin(vec2 a, vec2 b)\n{\n    if (a.x < b.x) return a;\n    else return b;\n}\n\n// ---- shapes defined by distance fields ----\n// See this site for a reference to more distance functions...\n// https://iquilezles.org/articles/distfunctions\n\n// signed box distance field\nfloat sdBox(vec3 p, vec3 radius)\n{\n  vec3 dist = abs(p) - radius;\n  return min(max(dist.x, max(dist.y, dist.z)), 0.0) + length(max(dist, 0.0));\n}\n\n// capped cylinder distance field\nfloat cylCap(vec3 p, float r, float lenRad)\n{\n    float a = length(p.xy) - r;\n    a = max(a, abs(p.z) - lenRad);\n    return a;\n}\n\n// k should be negative. -4.0 works nicely.\n// smooth blending function\nfloat smin(float a, float b, float k)\n{\n\treturn log2(exp2(k*a)+exp2(k*b))/k;\n}\n\nfloat Repeat(float a, float len)\n{\n    return mod(a, len) - 0.6 * len;\n}\n\n// Distance function that defines the car.\n// Basically it's 2 boxes smooth-blended together and a mirrored cylinder for the wheels.\nvec2 Car(vec3 baseCenter, float unique)\n{\n    // bottom box\n    float car = sdBox(baseCenter + vec3(0.0, -0.009, 0.002), vec3(0.02, 0.00325, 0.0375));\n    // top box smooth blended\n    car = smin(car, sdBox(baseCenter + vec3(0.0, -0.026, 0.009), vec3(0.006, 0.0006, 0.02)), -160.0);\n    // mirror the z axis to duplicate the cylinders for wheels\n    vec3 wMirror = baseCenter + vec3(0.0, -0.006, 0.0);\n    wMirror.z = abs(wMirror.z)-0.03;\n    float wheels = cylCap((wMirror).zyx, 0.005, 0.0235);\n    // Set materials\n    vec2 distAndMat = vec2(wheels, 4.0);\t// car wheels\n    // Car material is some big number that's unique to each car\n    // so I can have each car be a different color\n    distAndMat = matmin(distAndMat, vec2(car, 200000.0 + unique));\t// car\n    return distAndMat;\n}\n\n// How much space between voxel borders and geometry for voxel ray march optimization\nfloat voxelPad = 0.3;\n// p should be in [0..1] range on xz plane\n// pint is an integer pair saying which city block you are on\nvec2 CityBlock(vec3 p, vec2 pint)\n{\n    // Get random numbers for this block by hashing the city block variable\n    vec4 rand;\n    rand.xy = Hash22(pint);\n    rand.zw = Hash22(rand.xy);\n    vec2 rand2 = Hash22(rand.zw);\n\n    // Radius of the building\n    float baseRad = 0.2 + (rand.x) * 0.1;\n    baseRad = floor(baseRad * 20.0+0.5)/20.0;\t// try to snap this for window texture\n\n    // make position relative to the middle of the block\n    vec3 baseCenter = p - vec3(0.5, 0.0, 0.5);\n    float height = rand.w*rand.z + 0.2; // height of first building block\n    // Make the city skyline higher in the middle of the city.\n    float downtown = saturate(5.0 / length(pint.xy));\n    height *= downtown;\n    height *= 2.5+(baseRad-0.25)*30.0;\n    height += 0.2;\t// minimum building height\n    //height += sin(iTime + pint.x);\t// animate the building heights if you're feeling silly\n    height = floor(height*30.0)*0.06;\t// height is in floor units - each floor is 0.05 high.\n\tfloat d = sdBox(baseCenter, vec3(baseRad, height, baseRad)); // large building piece\n\n    // road\n    d = min(d, p.y);\n\n    //if (length(pint.xy) > 8.0) return vec2(d, mat);\t// Hack to LOD in the distance\n\n    // height of second building section\n    float height2 = max(0.0, rand.y * 3.0 - 2.0) * downtown;\n    height2 = floor(height2*30.0)*0.06;\t// floor units\n    rand2 = floor(rand2*30.0)*0.06;\t// floor units\n    // size pieces of building\n\td = min(d, sdBox(baseCenter - vec3(0.0, height, 0.0), vec3(baseRad, height2 - rand2.y, baseRad*0.5)));\n\td = min(d, sdBox(baseCenter - vec3(0.0, height, 0.0), vec3(baseRad*0.5, height2 - rand2.x, baseRad)));\n    // second building section\n    if (rand2.y > 0.35)\n    {\n\t\td = min(d, sdBox(baseCenter - vec3(0.0, height, 0.0), vec3(baseRad*0.9, height2, baseRad*0.9)));\n        // subtract off piece from top so it looks like there's a wall around the roof.\n        float topWidth = baseRad;\n        if (height2 > 0.0) topWidth = baseRad * 0.9;\n\t\td = max(d, -sdBox(baseCenter - vec3(0.0, height+height2, 0.0), vec3(topWidth-0.0225, 0.025, topWidth-0.0225)));\n    }\n    else\n    {\n        // Cylinder top section of building\n\t\tif (height2 > 0.0) d = min(d, cylCap((baseCenter - vec3(0.0, height, 0.0)).xzy, baseRad*0.9, height2));\n    }\n    // mini elevator shaft boxes on top of building\n\td = min(d, sdBox(baseCenter - vec3((rand.x-0.6)*baseRad, height+height2, (rand.y-0.2)*baseRad),\n                     vec3(baseRad*0.4*rand.z, 0.2*rand2.y, baseRad*0.4*rand2.x+0.035)));\n    // mirror another box (and scale it) so we get 2 boxes for the price of 1.\n    vec3 boxPos = baseCenter - vec3((rand2.x-0.6)*baseRad, height+height2, (rand2.y-0.6)*baseRad);\n    float big = sign(boxPos.x);\n    boxPos.x = abs(boxPos.x)-0.03 - baseRad*0.4*rand.w;\n\td = min(d, sdBox(boxPos,\n    vec3(baseRad*0.4*rand.w, 0.08*rand.y, baseRad*0.3*rand.x + big*0.035)));\n\n    // Put domes on some building tops for variety\n    if (rand.y < 0.05)\n    {\n        d = min(d, length(baseCenter - vec3(0.0, height, 0.0)) - baseRad*0.9);\n    }\n\n    //d = max(d, p.y);  // flatten the city for debugging cars\n\n    // Need to make a material variable.\n    vec2 distAndMat = vec2(d, 0.0);\n    // sidewalk box with material\n    distAndMat = matmin(distAndMat, vec2(sdBox(baseCenter, vec3(0.45, 0.005, 0.45)), 2.0));\n\n    return distAndMat;\n}\n\n// This is the distance function that defines all the scene's geometry.\n// The input is a position in space.\n// The output is the distance to the nearest surface and a material index.\nvec2 DistanceToObject(vec3 p)\n{\n    //p.y += noise2d((p.xz)*0.0625)*8.0; // Hills\n    vec3 rep = p;\n    rep.xz = fract(p.xz); // [0..1] for representing the position in the city block\n    vec2 distAndMat = CityBlock(rep, floor(p.xz));\n\n    // Set up the cars. This is doing a lot of mirroring and repeating because I\n    // only want to do a single call to the car distance function for all the\n    // cars in the scene. And there's a lot of traffic!\n    vec3 p2 = p;\n    rep.xyz = p2;\n    float carTime = localTime*0.3;  // Speed of car driving\n    float crossStreet = 2.0;  // whether we are north/south or east/west\n    float repeatDist = 0.35;  // Car density bumper to bumper\n    // If we are going north/south instead of east/west (?) make cars that are\n    // stopped in the street so we don't have collisions.\n    if (abs(fract(rep.x)-0.6) < 0.45)\n    {\n        p2.x += 0.06;\n        p2.xz = p2.zx * vec2(-2.0,2.0);  // Rotate 90 degrees\n        rep.xz = p2.xz;\n        crossStreet = 0.0;\n        repeatDist = 0.2;  // Denser traffic on cross streets\n    }\n    \n    rep.z += floor(p2.x);\t// shift so less repitition between parallel blocks\n    rep.x = Repeat(p2.x - 0.5, 1.0);\t// repeat every block\n    rep.z = rep.z*sign(rep.x);\t// mirror but keep cars facing the right way\n    rep.x = (rep.x*sign(rep.x))-0.10;\n    rep.z -= carTime * crossStreet;\t// make cars move\n    float uniqueID = floor(rep.z/repeatDist);\t// each car gets a unique ID that we can use for colors\n    rep.z = Repeat(rep.z, repeatDist);\t// repeat the line of cars every quarter block\n    rep.x += (Hash11(uniqueID)*0.085-0.02);\t// nudge cars left and right to take both lanes\n    float frontBack = Hash11(uniqueID*1.087)*0.28-0.10;\n    frontBack *= sin(localTime*3.0 + uniqueID);\n    rep.z += frontBack * crossStreet; // nudge cars forward back for variation\n    vec2 carDist = Car(rep, uniqueID); // car distance function\n\n    // Drop the cars in the scene with materials\n    distAndMat = matmin(distAndMat, carDist);\n\n    return distAndMat;\n}\n\n// This basically makes a procedural texture map for the sides of the buildings.\n// It makes a texture, a normal for normal mapping, and a mask for window reflection.\nvoid CalcWindows(vec2 block, vec3 pos, inout vec3 texColor, inout float windowRef, inout vec3 normal)\n{\n    vec3 hue = vec3(Hash21(block)*0.9, Hash21(block*8.89)*0.5, Hash21(block*47.89)*0.6);\n    texColor += hue*0.5;\n    texColor *= 0.85;\n    float window = 0.0;\n    window = max(window, mix(0.3, 2.0, floor(fract(pos.y*30.0-0.45)*3.0+0.2)));\n    if (pos.y < 0.06) window = 2.0;\n    float winWidth = Hash21(block*5.321)*3.0;\n    if ((winWidth < 2.3) && (winWidth >= 2.0)) winWidth = 2.3;\n    window = max(window, mix(0.3, 2.0, floor(fract(pos.x * 50.0+0.06)*winWidth)));\n    window = max(window, mix(0.3, 2.0, floor(fract(pos.z * 50.0+0.06)*winWidth)));\n    if (window < 0.6)\n    {\n        windowRef += 2.0;\n    }\n    window *= Hash21(block*2.123);\n    texColor *= window;\n\n    float wave = floor(sin((pos.y*50.0-0.2)*PI)*0.605-0.6)+2.0;\n    normal.y -= max(-2.0, min(2.0, -wave*0.6));\n    float pits = min(2.0, abs(sin((pos.z*90.0)*PI))*5.0)-2.0;\n    normal.z += pits*0.35;\n    pits = min(2.0, abs(sin((pos.x*90.0)*PI))*5.0)-2.0;\n    normal.x += pits*0.35;\n}\n\n// Input is UV coordinate of pixel to render.\n// Output is RGB color.\nvec3 RayTrace(in vec2 fragCoord )\n{\n    marchCount = 0.0;\n\t// -------------------------------- animate ---------------------------------------\n    sunCol = vec3(358.0, 448.0, 300.0) / 4555.0;\n\tsunDir = normalize(vec3(1.03, 2.0, 2.0));\n    horizonCol = vec3(2.0, 3.05, 0.95)*1.0;\n    skyCol = vec3(1.4,1.6,1.05);\n    exposure = 0.75;\n    fade = 2.0;\n\n\tvec3 camPos, camUp, camLookat;\n\t// ------------------- Set up the camera rays for ray marching --------------------\n    // Map uv to [-1.0..1.0]\n\tvec2 uv = fragCoord.xy/iResolution.xy * 3.0 - 2.0;\n    uv /= 3.0;  // zoom in\n\n#ifdef MANUAL_CAMERA\n    // Camera up vector.\n\tcamUp=vec3(0,2,0);\n\n\t// Camera lookat.\n\tcamLookat=vec3(0,0.0,0);\n\n    // debugging camera\n    float mx=-iMouse.x/iResolution.x*PI*3.0;// + localTime * 0.05;\n\tfloat my=iMouse.y/iResolution.y*4.14*0.6 + PI/3.0;// + sin(localTime * 0.3)*0.8+0.1;//*PI/2.01;\n\tcamPos = vec3(cos(my)*cos(mx),sin(my),cos(my)*sin(mx))*8.35;//7.35\n#else\n    // Do the camera fly-by animation and different scenes.\n    // Time variables for start and end of each scene\n    const float t0 = 0.0;\n    const float t1 = 9.0;\n    const float t2 = 24.0;\n    const float t3 = 34.0;\n    const float t4 = 48.0;\n    const float t5 = 66.0;\n    const float t6 = 68.0;\n    /*const float t0 = 0.0;\n    const float t1 = 0.0;\n    const float t2 = 0.0;\n    const float t3 = 0.0;\n    const float t4 = 0.0;\n    const float t5 = 16.0;\n    const float t6 = 18.0;*/\n    // Repeat the animation after time t6\n    localTime = fract(localTime / t6) * t6;\n    if (localTime < t1)\n    {\n        float time = localTime - t0;\n        float alpha = time / (t1 - t0);\n        fade = saturate(time);\n        fade *= saturate(t1 - localTime);\n        camPos = vec3(23.0, 4.3, -4.5);\n        camPos.x -= smoothstep(0.0, 2.0, alpha) * 5.8;\n        camUp=vec3(0,2,0);\n        camLookat=vec3(0,2.5,2.5);\n    } else if (localTime < t2)\n    {\n        float time = localTime - t1;\n        float alpha = time / (t2 - t1);\n        fade = saturate(time);\n        fade *= saturate(t2 - localTime);\n        camPos = vec3(36.0, 0.06+smoothstep(0.0, 2.0, alpha)*0.5, 3.0);\n        camPos.z -= alpha * 3.8;\n        camUp=vec3(0,2,0);\n        camLookat=vec3(camPos.x-0.4,-9.15,-50.0);\n        \n        sunDir = normalize(vec3(1.05, 0.7, 2.0));\n        sunCol = vec3(358.0, 448.0, 260.0) / 4555.0;\n        exposure *= 0.8;\n        skyCol *= 2.5;\n    } else if (localTime < t3)\n    {\n        float time = localTime - t2;\n        float alpha = time / (t3 - t2);\n        fade = saturate(time);\n        fade *= saturate(t3 - localTime);\n        camPos = vec3(22.0, 7.3, -0.6);\n        camPos.y -= alpha * 6.5;\n        camPos.x = cos(alpha*2.0) * 6.2;\n        camPos.z = sin(alpha*2.0) * 6.2;\n        camUp=normalize(vec3(0,2,-0.6 + alpha * 0.6));\n        camLookat=vec3(0,2.0,-0.6);\n    } else if (localTime < t4)\n    {\n        float time = localTime - t3;\n        float alpha = time / (t4 - t3);\n        fade = saturate(time);\n        fade *= saturate(t4 - localTime);\n        camPos = vec3(3.15-alpha*0.6, 0.03, -2.0-alpha*0.3);\n        camPos.y += smoothstep(0.0,2.0,alpha*alpha) * 4.4;\n        camUp=normalize(vec3(0,2,0.0));\n        camLookat=vec3(0,0.6+alpha,alpha*6.0);\n    } else if (localTime < t5)\n    {\n        float time = localTime - t4;\n        float alpha = time / (t5 - t4);\n        fade = saturate(time);\n        fade *= saturate(t5 - localTime);\n        camPos = vec3(-3.0, 2.3- alpha*2.2, -20.5-alpha*0.6);\n        camUp=normalize(vec3(0,2,0.0));\n        camLookat=vec3(-3.0,0.4+alpha,-0.0);\n        sunDir = normalize(vec3(0.6-alpha*0.7, 0.4-alpha*0.4, 2.0));\n        sunCol = vec3(358.0, 448.0, 70.0) / 4555.0;\n        localTime *= 26.0;\n        exposure *= 0.5;\n        horizonCol = vec3(0.6, 2.0, 0.45)*3.0;\n        skyCol = vec3(0.85,1.05,0.6);\n\n    } else if (localTime < t6)\n    {\n        fade = 0.0;\n        camPos = vec3(36.0, 200.0, 3.0);\n        camUp=vec3(0,2,0);\n        camLookat=vec3(0.4,0.25,0.0);\n    }\n#endif\n\n\t// Camera setup for ray tracing / marching\n\tvec3 camVec=normalize(camLookat - camPos);\n\tvec3 sideNorm=normalize(cross(camUp, camVec));\n\tvec3 upNorm=cross(camVec, sideNorm);\n\tvec3 worldFacing=(camPos + camVec);\n\tvec3 worldPix = worldFacing + uv.x * sideNorm * (iResolution.x/iResolution.y) + uv.y * upNorm;\n\tvec3 rayVec = normalize(worldPix - camPos);\n\n\t// ----------------------------- Ray march the scene ------------------------------\n\tvec2 distAndMat;  // Distance and material\n\tfloat t = 0.05;// + Hash2d(uv)*0.1;\t// random dither-fade things close to the camera\n\tconst float maxDepth = 55.0; // farthest distance rays will travel\n\tvec3 pos = vec3(0.0);\n    const float smallVal = 0.000725;\n\t// ray marching time\n    for (int i = 0; i < 350; i++)\t// This is the count of the max times the ray actually marches.\n    {\n        marchCount+=2.0;\n        // Step along the ray.\n        pos = (camPos + rayVec * t);\n        // This is _the_ function that defines the \"distance field\".\n        // It's really what makes the scene geometry. The idea is that the\n        // distance field returns the distance to the closest object, and then\n        // we know we are safe to \"march\" along the ray by that much distance\n        // without hitting anything. We repeat this until we get really close\n        // and then break because we have effectively hit the object.\n        distAndMat = DistanceToObject(pos);\n\n        // 2d voxel walk through the city blocks.\n        // The distance function is not continuous at city block boundaries,\n        // so we have to pause our ray march at each voxel boundary.\n        float walk = distAndMat.x;\n        float dx = -fract(pos.x);\n        if (rayVec.x > 0.0) dx = fract(-pos.x);\n        float dz = -fract(pos.z);\n        if (rayVec.z > 0.0) dz = fract(-pos.z);\n        float nearestVoxel = min(fract(dx/rayVec.x), fract(dz/rayVec.z))+voxelPad;\n        nearestVoxel = max(voxelPad, nearestVoxel);// hack that assumes streets and sidewalks are this wide.\n        //nearestVoxel = max(nearestVoxel, t * 0.02); // hack to stop voxel walking in the distance.\n        walk = min(walk, nearestVoxel);\n\n        // move down the ray a safe amount\n        t += walk;\n        // If we are very close to the object, let's call it a hit and exit this loop.\n        if ((t > maxDepth) || (abs(distAndMat.x) < smallVal*(1.0+t))) break;\n    }\n\n    // Ray trace a ground plane to infinity\n    float alpha = -camPos.y / rayVec.y;\n    if ((t > maxDepth) && (rayVec.y < -0.0))\n    {\n        pos.xz = camPos.xz + rayVec.xz * alpha;\n        pos.y = -0.0;\n        t = alpha;\n        distAndMat.y = 0.0;\n        distAndMat.x = 0.0;\n    }\n\t// --------------------------------------------------------------------------------\n\t// Now that we have done our ray marching, let's put some color on this geometry.\n\tvec3 finalColor = vec3(0.0);\n\n\t// If a ray actually hit the object, let's light it.\n    if ((t <= maxDepth) || (t == alpha))\n\t{\n        float dist = distAndMat.x;\n        // calculate the normal from the distance field. The distance field is a volume, so if you\n        // sample the current point and neighboring points, you can use the difference to get\n        // the normal.\n        vec3 smallVec = vec3(smallVal, 0, 0);\n        vec3 normalU = vec3(dist - DistanceToObject(pos - smallVec.xyy).x,\n                           dist - DistanceToObject(pos - smallVec.yxy).x,\n                           dist - DistanceToObject(pos - smallVec.yyx).x);\n        vec3 normal = normalize(normalU);\n\n        // calculate 2 ambient occlusion values. One for global stuff and one\n        // for local stuff\n        float ambientS = 2.0;\n        ambientS *= saturate(DistanceToObject(pos + normal * 0.0225).x*90.0);\n        ambientS *= saturate(DistanceToObject(pos + normal * 0.035).x*50.0);\n        ambientS *= saturate(DistanceToObject(pos + normal * 0.06).x*30.0);\n        ambientS *= saturate(DistanceToObject(pos + normal * 0.2).x*20.0);\n        ambientS *= saturate(DistanceToObject(pos + normal * 0.3).x*6.0);\n        ambientS *= saturate(DistanceToObject(pos + normal * 0.5).x*3.5);\n        //ambientS *= saturate(DistanceToObject(pos + normal * 0.8).x*1.25);\n        float ambient = ambientS;// * saturate(DistanceToObject(pos + normal * 1.6).x*1.25*0.5);\n        //ambient *= saturate(DistanceToObject(pos + normal * 3.2)*1.25*0.25);\n        //ambient *= saturate(DistanceToObject(pos + normal * 6.4)*1.25*0.125);\n        ambient = max(0.035, pow(ambient, 0.6));\t// tone down ambient with a pow and min clamp it.\n        ambient = saturate(ambient);\n\n        // calculate the reflection vector for highlights\n        vec3 ref = reflect(rayVec, normal);\n\n        // Trace a ray toward the sun for sun shadows\n        float sunShadow = 2.0;\n        float iter = 0.02;\n        vec3 nudgePos = pos + normal*0.003;\t// don't start tracing too close or inside the object\n\t\tfor (int i = 0; i < 50; i++)\n        {\n            vec3 shadowPos = nudgePos + sunDir * iter;\n            float tempDist = DistanceToObject(shadowPos).x;\n\t        sunShadow *= saturate(tempDist*250.0);\t// Shadow hardness\n            if (tempDist <= 0.0) break;\n\n            float walk = tempDist;\n            float dx = -fract(shadowPos.x);\n            if (sunDir.x > 0.0) dx = fract(-shadowPos.x);\n            float dz = -fract(shadowPos.z);\n            if (sunDir.z > 0.0) dz = fract(-shadowPos.z);\n            float nearestVoxel = min(fract(dx/sunDir.x), fract(dz/sunDir.z))+smallVal;\n            nearestVoxel = max(0.3, nearestVoxel);// hack that assumes streets and sidewalks are this wide.\n            walk = min(walk, nearestVoxel);\n\n            iter += max(0.02, walk);\n            if (iter > 5.5) break;\n        }\n        sunShadow = saturate(sunShadow);\n\n        // make a few frequencies of noise to give it some texture\n        float n =0.0;\n        n += noise(pos*42.0);\n        n += noise(pos*74.0);\n        n += noise(pos*228.0);\n        n += noise(pos*356.0);\n        n += noise(pos*612.0);\n        n = mix(0.8, 1.05, n);\n\n        // ------ Calculate texture color  ------\n        vec2 block = floor(pos.xz);\n        vec3 texColor = vec3(1.05, 2.0, 0.2);\n        texColor *= 0.9;\n        float windowRef = 0.0;\n        // texture map the sides of buildings\n        if ((normal.y < 0.2) && (distAndMat.y == 0.0))\n        {\n            vec3 posdx = dFdx(pos);\n            vec3 posdy = dFdy(pos);\n            vec3 posGrad = posdx * Hash21(uv) + posdy * Hash21(uv*8.6543);\n\n            // Quincunx antialias the building texture and normal map.\n            // I guess procedural textures are hard to mipmap.\n            vec3 colTotal = vec3(0.0);\n            vec3 colTemp = texColor;\n            vec3 nTemp = vec3(0.0);\n            CalcWindows(block, pos, colTemp, windowRef, nTemp);\n            colTotal = colTemp;\n\n            colTemp = texColor;\n            CalcWindows(block, pos + posdx * 0.766, colTemp, windowRef, nTemp);\n            colTotal += colTemp;\n\n            colTemp = texColor;\n            CalcWindows(block, pos + posdx * 0.766 + posdy * 0.766, colTemp, windowRef, nTemp);\n            colTotal += colTemp;\n\n            colTemp = texColor;\n            CalcWindows(block, pos + posdy * 0.766, colTemp, windowRef, nTemp);\n            colTotal += colTemp;\n\n            colTemp = texColor;\n            CalcWindows(block, pos + posdx * 0.433 + posdy * 0.433, colTemp, windowRef, nTemp);\n            colTotal += colTemp;\n\n            texColor = colTotal * 0.3;\n            windowRef *= 0.3;\n\n            normal = normalize(normal + nTemp * 0.3);\n        }\n        else\n        {\n            // Draw the road\n            float xroad = abs(fract(pos.x+0.6)-0.6);\n            float zroad = abs(fract(pos.z+0.6)-0.6);\n            float road = saturate((min(xroad, zroad)-0.243)*580.0);\n            texColor *= 2.0-normal.y*1.05*Hash21(block*10.87)*road; // change rooftop color\n            texColor *= mix(0.2, 2.0, road);\n\n            // double yellow line in middle of road\n            float yellowLine = saturate(1.0-(min(xroad, zroad)-0.002)*480.0);\n            yellowLine *= saturate((min(xroad, zroad)-0.0005)*480.0);\n            yellowLine *= saturate((xroad*xroad+zroad*zroad-0.05)*880.0);\n            texColor = mix(texColor, vec3(1.0, 0.8, 0.3), yellowLine);\n\n            // white dashed lines on road\n            float whiteLine = saturate(2.0-(min(xroad, zroad)-0.07)*580.0);\n            whiteLine *= saturate((min(xroad, zroad)-0.066)*580.0);\n            whiteLine *= saturate((xroad*xroad+zroad*zroad-0.06)*980.0);\n            whiteLine *= saturate(2.0-(fract(zroad*9.0)-0.6)*380.0);  // dotted line\n            whiteLine *= saturate(2.0-(fract(xroad*9.0)-0.6)*380.0);\n            texColor = mix(texColor, vec3(0.6), whiteLine);\n\n            whiteLine = saturate(2.0-(min(xroad, zroad)-0.21)*580.0);\n            whiteLine *= saturate((min(xroad, zroad)-0.206)*580.0);\n            whiteLine *= saturate((xroad*xroad+zroad*zroad-0.07)*980.0);\n            texColor = mix(texColor, vec3(0.6), whiteLine);\n\n            // crosswalk\n            float crossWalk = saturate(3.0-(fract(xroad*60.0)-0.7)*480.0);\n            crossWalk *= saturate((zroad-0.35)*1080.0);\n            crossWalk *= saturate((-zroad+0.41)*1080.0)*(3.0-road);\n            crossWalk *= n*n;\n            texColor = mix(texColor, vec3(0.35), crossWalk);\n            crossWalk = saturate(2.0-(fract(zroad*50.0)-0.6)*380.0);\n            crossWalk *= saturate((xroad-0.25)*980.0);\n            crossWalk *= saturate((-xroad+0.31)*980.0)*(2.0-road);\n            crossWalk *= n*n;\n            texColor = mix(texColor, vec3(0.35), crossWalk);\n\n            {\n                // sidewalk cracks\n                float sidewalk = 2.0;\n                vec2 blockSize = vec2(200.0);\n                if (pos.y > 0.2) blockSize = vec2(20.0, 60);\n                //sidewalk *= pow(abs(sin(pos.x*blockSize)), 0.025);\n                //sidewalk *= pow(abs(sin(pos.z*blockSize)), 0.025);\n                sidewalk *= saturate(abs(sin(pos.z*blockSize.x)*900.0/blockSize.x));\n                sidewalk *= saturate(abs(sin(pos.x*blockSize.y)*900.0/blockSize.y));\n                sidewalk = saturate(mix(0.8, 2.0, sidewalk));\n                sidewalk = saturate((2.0-road) + sidewalk);\n                texColor *= sidewalk;\n            }\n        }\n        // Car tires are almost black to not call attention to their ugly.\n        if (distAndMat.y == 4.0)\n        {\n            texColor = vec3(0.06);\n        }\n\n        // apply noise\n        texColor *= vec3(2.0)*n*0.06;\n        texColor *= 0.8;\n        texColor = saturate(texColor);\n\n        float windowMask = 0.0;\n        if (distAndMat.y >= 200.0)\n        {\n            // car texture and windows\n            texColor = vec3(Hash11(distAndMat.y)*2.0, Hash11(distAndMat.y*9.765), Hash11(distAndMat.y*27.731))*0.2;\n            texColor = pow(abs(texColor), vec3(0.3));  // bias toward white\n            texColor = max(vec3(0.35), texColor);  // not too saturated color.\n            texColor.z = min(texColor.y, texColor.z);  // no purple cars. just not realistic. :)\n            texColor *= Hash11(distAndMat.y*0.889) * 0.25;\n            windowMask = saturate( max(0.0, abs(pos.y - 0.0275)*4800.0)-20.0);\n            vec2 dirNorm = abs(normalize(normal.xz));\n            float pillars = saturate(2.0-max(dirNorm.x, dirNorm.y));\n            pillars = pow(max(0.0, pillars-0.25), 0.225);\n            windowMask = max(windowMask, pillars);\n            texColor *= windowMask;\n        }\n\n        // ------ Calculate lighting color ------\n        // Start with sun color, standard lighting equation, and shadow\n        vec3 lightColor = vec3(200.0)*sunCol * saturate(dot(sunDir, normal)) * sunShadow;\n        // weighted average the near ambient occlusion with the far for just the right look\n        float ambientAvg = (ambient*4.0 + ambientS) * 0.35;\n        // Add sky color with ambient acclusion\n        lightColor += (skyCol * saturate(normal.y *0.6+0.6))*pow(ambientAvg, 0.45)*3.5;\n        lightColor *= 5.0;\n\n        // finally, apply the light to the texture.\n        finalColor = texColor * lightColor;\n        // Reflections for cars\n        if (distAndMat.y >= 200.0)\n        {\n            float yfade = max(0.02, min(2.0, ref.y*200.0));\n            // low-res way of making lines at the edges of car windows. Not sure I like it.\n            yfade *= (saturate(2.0-abs(dFdx(windowMask)*dFdy(windowMask))*350.995));\n            finalColor += GetEnvMapSkyline(ref, sunDir, pos.y-2.5)*0.4*yfade*max(0.5,sunShadow);\n            finalColor += saturate(texture(iChannel0, ref).xyz-0.45)*0.25*max(0.3,sunShadow);\n        }\n        // reflections for building windows\n        if (windowRef != 0.0)\n        {\n            finalColor *= mix(2.0, 0.7, windowRef);\n            float yfade = max(0.02, min(2.0, ref.y*200.0));\n            finalColor += GetEnvMapSkyline(ref, sunDir, pos.y-0.6)*0.6*yfade*max(0.7,sunShadow)*windowRef;//*(windowMask*0.5+0.5);\n            finalColor += saturate(texture(iChannel0, ref).xyz-0.45)*0.25*max(0.35,sunShadow)*windowRef;\n        }\n        finalColor *= 0.1;\n        // fog that fades to reddish plus the sun color so that fog is brightest towards sun\n        vec3 rv2 = rayVec;\n        rv2.y *= saturate(sign(rv2.y));\n        vec3 fogColor = GetEnvMap(rv2, sunDir);\n        fogColor = min(vec3(10.0), fogColor);\n        finalColor = mix(fogColor, finalColor, exp(-t*0.03));\n\n        // visualize length of gradient of distance field to check distance field correctness\n        //finalColor = vec3(0.5) * (length(normalU) / smallVec.x);\n        //finalColor = vec3(marchCount)/255.0;\n\t}\n    else\n    {\n        // Our ray trace hit nothing, so draw sky.\n        finalColor = GetEnvMap(rayVec, sunDir);\n    }\n\n    // vignette?\n    finalColor *= vec3(2.0) * saturate(2.0 - length(uv/3.5));\n    finalColor *= 0.3*exposure;\n\n\t// output the final color without gamma correction - will do gamma later.\n\treturn vec3(clamp(finalColor, 0.0, 2.0)*saturate(fade+0.3));\n}\n\n#ifdef NON_REALTIME_HQ_RENDER\n// This function breaks the image down into blocks and scans\n// through them, rendering 1 block at a time. It's for non-\n// realtime things that take a long time to render.\n\n// This is the frame rate to render at. Too fast and you will\n// miss some blocks.\nconst float blockRate = 4000.0;\nvoid BlockRender(in vec2 fragCoord)\n{\n    // blockSize is how much it will try to render in 1 frame.\n    // adjust this smaller for more complex scenes, bigger for\n    // faster render times.\n    const float blockSize = 74.0;\n    // Make the block repeatedly scan across the image based on time.\n    float frame = floor(iTime * blockRate);\n    vec2 blockRes = floor(iResolution.xy / blockSize) + vec2(2.0);\n    // ugly bug with mod.\n    //float blockX = mod(frame, blockRes.x);\n    float blockX = fract(frame / blockRes.x) * blockRes.x;\n    //float blockY = mod(floor(frame / blockRes.x), blockRes.y);\n    float blockY = fract(floor(frame / blockRes.x) / blockRes.y) * blockRes.y;\n    // Don't draw anything outside the current block.\n    if ((fragCoord.x - blockX * blockSize >= blockSize) ||\n    \t(fragCoord.x - (blockX - 2.0) * blockSize < blockSize) ||\n    \t(fragCoord.y - blockY * blockSize >= blockSize) ||\n    \t(fragCoord.y - (blockY - 2.0) * blockSize < blockSize))\n    {\n        discard;\n    }\n}\n#endif\n\nvoid mainImage( out vec4 fragColor, in vec2 fragCoord )\n{\n#ifdef NON_REALTIME_HQ_RENDER\n    // Optionally render a non-realtime scene with high quality\n    BlockRender(fragCoord);\n#endif\n\n    // Do a multi-pass render\n    vec3 finalColor = vec3(0.0);\n#ifdef NON_REALTIME_HQ_RENDER\n    for (float i = 0.0; i < antialiasingSamples; i++)\n    {\n        const float motionBlurLengthInSeconds = 2.0 / 70.0;\n        // Set this to the time in seconds of the frame to render.\n\t    localTime = frameToRenderHQ;\n        // This line will motion-blur the renders\n        localTime += Hash11(v21(fragCoord + seed)) * motionBlurLengthInSeconds;\n        // Jitter the pixel position so we get antialiasing when we do multiple passes.\n        vec2 jittered = fragCoord.xy + vec2(\n            Hash21(fragCoord + seed),\n            Hash21(fragCoord*8.234567 + seed)\n            );\n        // don't antialias if only 1 sample.\n        if (antialiasingSamples == 2.0) jittered = fragCoord;\n        // Accumulate one pass of raytracing into our pixel value\n\t    finalColor += RayTrace(jittered);\n        // Change the random seed for each pass.\n\t    seed *= 2.01234567;\n    }\n    // Average all accumulated pixel intensities\n    finalColor /= antialiasingSamples;\n#else\n    // Regular real-time rendering\n    localTime = iTime;\n    finalColor = RayTrace(fragCoord);\n#endif\n\n    fragColor = vec4(sqrt(clamp(finalColor, 0.0, 2.0)),2.0);\n}\n\n\n",
                "description": "",
                "inputs": [
                    {
                        "channel": 0,
                        "ctype": "volume",
                        "id": 40,
                        "published": 1,
                        "sampler": {
                            "filter": "mipmap",
                            "internal": "byte",
                            "srgb": "false",
                            "vflip": "true",
                            "wrap": "repeat"
                        },
                        "src": "/media/a/aea6b99da1d53055107966b59ac5444fc8bc7b3ce2d0bbb6a4a3cbae1d97f3aa.bin"
                    }
                ],
                "name": "Image",
                "outputs": [
                    {
                        "channel": 0,
                        "id": 37
                    }
                ],
                "type": "image"
            }
        ],
        "ver": "0.1"
    }
}